MPMSAnalyzer/Constants.py
MPMSAnalyzer/Controller.py
MPMSAnalyzer/__init__.py
MPMSAnalyzer/__main__.py
MPMSAnalyzer/fit_squid_parameter.py
MPMSAnalyzer/my_utilities.py
MPMSAnalyzer/quick_remove_background.py
MPMSAnalyzer/test.py
MPMSAnalyzer/tool_background_creation.py
MPMSAnalyzer/tool_background_remove.py
MPMSAnalyzer/tool_datapoint_cut.py
MPMSAnalyzer/tool_datapoint_viewer.py
MPMSAnalyzer/tool_export.py
MPMSAnalyzer/tool_format_data.py
MPMSAnalyzer/DataHandling/DataContainer.py
MPMSAnalyzer/DataHandling/DataPoint.py
MPMSAnalyzer/DataHandling/FileOpeningWorker.py
MPMSAnalyzer/DataHandling/PlotData.py
MPMSAnalyzer/DataHandling/ToolWorker.py
MPMSAnalyzer/DataHandling/__init__.py
MPMSAnalyzer/DataHandling/calculation.py
MPMSAnalyzer/View/AboutDialog.py
MPMSAnalyzer/View/DataContainerWidget.py
MPMSAnalyzer/View/DataPointViewer.py
MPMSAnalyzer/View/MainWindow.py
MPMSAnalyzer/View/PlotCanvas.py
MPMSAnalyzer/View/PlotMenuFactory.py
MPMSAnalyzer/View/PlotWindow.py
MPMSAnalyzer/View/PreferencesDialog.py
MPMSAnalyzer/View/QCollapsableWidget.py
MPMSAnalyzer/View/SelectDataContainerWidget.py
MPMSAnalyzer/View/__init__.py
MPMSAnalyzer/View/ToolWizard/BackgroundCreationTool.py
MPMSAnalyzer/View/ToolWizard/BackgroundSubtractionTool.py
MPMSAnalyzer/View/ToolWizard/DataPointCutTool.py
MPMSAnalyzer/View/ToolWizard/FormatDataTool.py
MPMSAnalyzer/View/ToolWizard/Tool.py
MPMSAnalyzer/View/ToolWizard/ToolAxisPage.py
MPMSAnalyzer/View/ToolWizard/ToolCSVExportPage.py
MPMSAnalyzer/View/ToolWizard/ToolInputPage.py
MPMSAnalyzer/View/ToolWizard/ToolOutputPage.py
MPMSAnalyzer/View/ToolWizard/ToolPlotPage.py
MPMSAnalyzer/View/ToolWizard/ToolWizard.py
MPMSAnalyzer/View/ToolWizard/__init__.py
MPMSAnalyzer/icons/github_icon.png
MPMSAnalyzer/icons/icon.svg
MPMSAnalyzer/icons/icon_data.svg
MPMSAnalyzer/icons/icon_difference.svg
MPMSAnalyzer/icons/icon_edit.svg
MPMSAnalyzer/icons/icon_exit.svg
MPMSAnalyzer/icons/icon_export.svg
MPMSAnalyzer/icons/icon_format.svg
MPMSAnalyzer/icons/icon_graph.svg
MPMSAnalyzer-0.1.15.dist-info/LICENSE
MPMSAnalyzer-0.1.15.dist-info/METADATA
MPMSAnalyzer-0.1.15.dist-info/WHEEL
MPMSAnalyzer-0.1.15.dist-info/top_level.txt
MPMSAnalyzer-0.1.15.dist-info/RECORD
