Metadata-Version: 2.1
Name: MPMSAnalyzer
Version: 0.1.15
Summary: A python program for analyzing SQUID DC raw data
Home-page: https://github.com/miile7/mpms-analyzer
Author: miile7
Author-email: miile7@gmx.de
License: UNKNOWN
Platform: UNKNOWN
Classifier: Programming Language :: Python :: 3
Classifier: Operating System :: OS Independent
Classifier: Topic :: Scientific/Engineering
Classifier: Intended Audience :: Education
Classifier: License :: Free For Educational Use
Classifier: Topic :: Scientific/Engineering :: Information Analysis
Requires-Python: >=3.7
License-File: LICENSE
Requires-Dist: matplotlib (>=3.1.3)
Requires-Dist: PyQt5 (>=5.9.2)
Requires-Dist: sip (>=4.19.8)
Requires-Dist: scipy (>=1.4.1)
Requires-Dist: numpy (>=1.18.1)
Requires-Dist: formlayout (>=1.2.0)
